{
  "configVersion": 1,
  "timestamp": 1613793877119,
  "index": "/index.html",
  "assetGroups": [
    {
      "name": "app",
      "installMode": "prefetch",
      "updateMode": "prefetch",
      "cacheQueryOptions": {
        "ignoreVary": true
      },
      "urls": [
        "/favicon.ico",
        "/index.html",
        "/main.45f0d2118a2124ac747b.js",
        "/manifest.webmanifest",
        "/polyfills.d15628b9ba7248669cd9.js",
        "/runtime.7b63b9fd40098a2e8207.js",
        "/styles.ac68e1bbd02dc441c5a0.css"
      ],
      "patterns": []
    },
    {
      "name": "assets",
      "installMode": "lazy",
      "updateMode": "prefetch",
      "cacheQueryOptions": {
        "ignoreVary": true
      },
      "urls": [
        "/check-in-success.b943a3959d352d0a071f.png",
        "/facemask.4927b6a37ff51c1edbac.png",
        "/home-enter.84f5e88387481ae6e008.jpg",
        "/home-report.0361afe837aedd21a878.jpg",
        "/home-taxi.e9b83a60d3d51d0da90a.jpg",
        "/icon-close.d53273f6911c12cfc4b7.png",
        "/icon-refresh.fffe24b3b7ded0ca4e44.png",
        "/onboard-scan-qr.b0731387e23309389732.png",
        "/qr-code.51fd08db7b019c601d4b.png",
        "/tabicons-icon-home-selected.1bdd8ca6546d9f321cc3.png",
        "/tabicons-icon-home.38463e22a862806c3d55.png",
        "/tabicons-icon-inbox-selected.df9b403e8587dca11790.png",
        "/tabicons-icon-inbox.6f0ce846899b36693b5a.png",
        "/tabicons-icon-settings-selected.1bf72ff05d5d6a9a8a4c.png",
        "/tabicons-icon-settings.7b6e1b8ea10b1fc12a92.png"
      ],
      "patterns": []
    }
  ],
  "dataGroups": [],
  "hashTable": {
    "/check-in-success.b943a3959d352d0a071f.png": "ffff4e0eb14f0325ec26003fd598fcdaaf0c2007",
    "/facemask.4927b6a37ff51c1edbac.png": "8ebdba6cd8f59fd76683a38927a1b23fe93fc904",
    "/favicon.ico": "531284c4cf5d1b6e7dadf42401d263f90f6d1b0a",
    "/home-enter.84f5e88387481ae6e008.jpg": "c0d796a555fa276ba5d32bca1f13e12cae176bdb",
    "/home-report.0361afe837aedd21a878.jpg": "dc57cfdea5d274c658ea1ef4f79235c1f43ea1bc",
    "/home-taxi.e9b83a60d3d51d0da90a.jpg": "8a8490594fcf81ebeb4ad4910c9e88ea7c50b335",
    "/icon-close.d53273f6911c12cfc4b7.png": "ff5fa13f6623597717f427e2d7d5c343660f3293",
    "/icon-refresh.fffe24b3b7ded0ca4e44.png": "dfcf4eb9133fdd9631d2e53743b8efa4606ac93d",
    "/index.html": "b92d4a9c83056d95559924944f1333ee0b819c12",
    "/main.45f0d2118a2124ac747b.js": "cb28b5fc7fac477e1b1de43a6bffbdd8f1fa97ba",
    "/manifest.webmanifest": "eaee7feb72e59d69e4c02365b7bd1da66b2edc4d",
    "/onboard-scan-qr.b0731387e23309389732.png": "12a7abd2af7192a84b474beecf66e23634a7c4e5",
    "/polyfills.d15628b9ba7248669cd9.js": "f888b31e000d9b05c8c3fef19c325d813f2b7e1b",
    "/qr-code.51fd08db7b019c601d4b.png": "960f5af989a29832de5259575f4f68f207fcaf06",
    "/runtime.7b63b9fd40098a2e8207.js": "a9aafcf49f49145093fc831efd9b8e2f6c71bb9c",
    "/styles.ac68e1bbd02dc441c5a0.css": "ad26379b3ef4948b970c6b80236626335ae03dde",
    "/tabicons-icon-home-selected.1bdd8ca6546d9f321cc3.png": "8d9bb59ae0235d8d92a49c531f16246922b4d462",
    "/tabicons-icon-home.38463e22a862806c3d55.png": "bea6f6623937a8641c7f66c03e591dafce97abe8",
    "/tabicons-icon-inbox-selected.df9b403e8587dca11790.png": "71cd4ab66d104da6d04bbd77e7675cef0d602b28",
    "/tabicons-icon-inbox.6f0ce846899b36693b5a.png": "7dd039ddd0f954f623d93f2e7fe736c9cc8f50ca",
    "/tabicons-icon-settings-selected.1bf72ff05d5d6a9a8a4c.png": "2d964392fa17000ad2a4987add08ea97a2db0afb",
    "/tabicons-icon-settings.7b6e1b8ea10b1fc12a92.png": "489ecf7fc194b8b71f5768a3a4dcda0f2e6e1a39"
  },
  "navigationUrls": [
    {
      "positive": true,
      "regex": "^\\/.*$"
    },
    {
      "positive": false,
      "regex": "^\\/(?:.+\\/)?[^/]*\\.[^/]*$"
    },
    {
      "positive": false,
      "regex": "^\\/(?:.+\\/)?[^/]*__[^/]*$"
    },
    {
      "positive": false,
      "regex": "^\\/(?:.+\\/)?[^/]*__[^/]*\\/.*$"
    }
  ],
  "navigationRequestStrategy": "performance"
}